flag_identification/__init__.py
flag_identification/constants.py
flag_identification/logging.py
flag_identification/settings.py
flag_identification/utils.py
flag_identification/bin/__init__.py
flag_identification/bin/move_additional_flags.py
flag_identification/bin/predict.py
flag_identification/bin/predict_single.py
flag_identification/bin/prep.py
flag_identification/bin/pull_wikimedia.py
flag_identification/bin/remove_dups.py
flag_identification/bin/train.py
flag_identification-0.0.7.dist-info/LICENSE
flag_identification-0.0.7.dist-info/METADATA
flag_identification-0.0.7.dist-info/WHEEL
flag_identification-0.0.7.dist-info/entry_points.txt
flag_identification-0.0.7.dist-info/top_level.txt
flag_identification-0.0.7.dist-info/RECORD
