Metadata-Version: 2.1
Name: flag-identification
Version: 0.0.7
Summary: Identify a flag by an image
Home-page: https://github.com/RobertLucey/flag-identification
Author: Robert Lucey
Requires-Python: >=3.6
License-File: LICENSE
Requires-Dist: imgaug
Requires-Dist: aspose-words
Requires-Dist: cairosvg
Requires-Dist: bs4
Requires-Dist: keras (==2.11.0)
Requires-Dist: tensorflow (==2.11.0)
Requires-Dist: cython
Requires-Dist: tqdm
Requires-Dist: requests
Requires-Dist: pandas
Requires-Dist: sklearn
Requires-Dist: scikit-learn
Requires-Dist: Pillow
Requires-Dist: opencv-python
